build_frontend.py
lynxkite_app/__init__.py
lynxkite_app/__main__.py
lynxkite_app/crdt.py
lynxkite_app/frontend_types.py
lynxkite_app/icons.py
lynxkite_app/main.py
lynxkite_app/web_assets/__init__.py
lynxkite_app/web_assets/index.html
lynxkite_app/web_assets/tabler-icons.json
lynxkite_app/web_assets/assets/3Dmol-C3Mwyz8-.js
lynxkite_app/web_assets/assets/3Dmol-C3Mwyz8-.js.map
lynxkite_app/web_assets/assets/__init__.py
lynxkite_app/web_assets/assets/favicon-DoC2fMLm.ico
lynxkite_app/web_assets/assets/index-Bh7zOVHW.css
lynxkite_app/web_assets/assets/index-BlxdVhSE.js
lynxkite_app/web_assets/assets/index-BlxdVhSE.js.map
lynxkite_app/web_assets/assets/index-CCO8YKYm.js
lynxkite_app/web_assets/assets/index-CCO8YKYm.js.map
lynxkite_app/web_assets/assets/inter-cyrillic-400-normal-HOLc17fK.woff
lynxkite_app/web_assets/assets/inter-cyrillic-400-normal-obahsSVq.woff2
lynxkite_app/web_assets/assets/inter-cyrillic-500-normal-BasfLYem.woff2
lynxkite_app/web_assets/assets/inter-cyrillic-500-normal-CxZf_p3X.woff
lynxkite_app/web_assets/assets/inter-cyrillic-ext-400-normal-BQZuk6qB.woff2
lynxkite_app/web_assets/assets/inter-cyrillic-ext-400-normal-DQukG94-.woff
lynxkite_app/web_assets/assets/inter-cyrillic-ext-500-normal-B0yAr1jD.woff2
lynxkite_app/web_assets/assets/inter-cyrillic-ext-500-normal-BmqWE9Dz.woff
lynxkite_app/web_assets/assets/inter-greek-400-normal-B4URO6DV.woff2
lynxkite_app/web_assets/assets/inter-greek-400-normal-q2sYcFCs.woff
lynxkite_app/web_assets/assets/inter-greek-500-normal-BIZE56-Y.woff2
lynxkite_app/web_assets/assets/inter-greek-500-normal-Xzm54t5V.woff
lynxkite_app/web_assets/assets/inter-greek-ext-400-normal-DGGRlc-M.woff2
lynxkite_app/web_assets/assets/inter-greek-ext-400-normal-KugGGMne.woff
lynxkite_app/web_assets/assets/inter-greek-ext-500-normal-2j5mBUwD.woff
lynxkite_app/web_assets/assets/inter-greek-ext-500-normal-C4iEst2y.woff2
lynxkite_app/web_assets/assets/inter-latin-400-normal-C38fXH4l.woff2
lynxkite_app-0.3.0.dist-info/METADATA
lynxkite_app-0.3.0.dist-info/WHEEL
lynxkite_app-0.3.0.dist-info/entry_points.txt
lynxkite_app-0.3.0.dist-info/top_level.txt
lynxkite_app-0.3.0.dist-info/RECORD
