Metadata-Version: 2.4
Name: lynxkite-app
Version: 0.3.0
Summary: The LynxKite application, with web server and UI
Project-URL: Homepage, https://github.com/lynxkite/lynxkite-2000/
Classifier: License :: OSI Approved :: GNU Affero General Public License v3 or later (AGPLv3+)
Requires-Python: >=3.11
Requires-Dist: fastapi[standard]>=0.115.6
Requires-Dist: griffe>=1.7.3
Requires-Dist: joblib>=1.5.1
Requires-Dist: lynxkite-core
Requires-Dist: pycrdt-websocket>=0.16
Requires-Dist: pycrdt>=0.12.26
Requires-Dist: pydantic>=2.11.7
Requires-Dist: sse-starlette>=2.2.1
Requires-Dist: uvicorn>=0.35.0
